main.v
module water_level_controller (
    input wire clk, reset,
    input wire low, mid, high,
    output reg motor_on
);

    parameter EMPTY   = 2'b00;
    parameter FILLING = 2'b01;
    parameter FULL    = 2'b10;

    reg [1:0] current_state, next_state;

    // State transition
    always @(posedge clk or posedge reset) begin
        if (reset)
            current_state <= EMPTY;
        else
            current_state <= next_state;
    end

    // Next state logic
    always @(*) begin
        case (current_state)
            EMPTY: begin
                motor_on = 1;
                if (low && mid && high)
                    next_state = FULL;
                else
                    next_state = FILLING;
            end
            FILLING: begin
                motor_on = 1;
                if (high)
                    next_state = FULL;
                else
                    next_state = FILLING;
            end
            FULL: begin
                motor_on = 0;
                if (!high)
                    next_state = FILLING;
                else
                    next_state = FULL;
            end
            default: begin
                motor_on = 0;
                next_state = EMPTY;
            end
        endcase
    end
endmodule

tb.v
module tb_water_level_controller();
reg clk, reset;
reg low, mid, high;
wire motor_on;
water_level_controller uut (
.clk(clk), .reset(reset),
.low(low), .mid(mid), .high(high),
.motor_on(motor_on)
);
always #5 clk = ~clk;
initial begin
$dumpfile("water_level.vcd");
$dumpvars(0, tb_water_level_controller);
end
initial begin
clk=0; reset=1; low=0; mid=0; high=0;
#10 reset=0;
#20 low=1; mid=0; high=0;
#20 low=1; mid=1; high=0;
#20 low=1; mid=1; high=1;
#20 low=1; mid=0; high=0;
#20 low=0; mid=0; high=0;
#20 $finish;
end
initial begin
$monitor("Time=%0t | LOW=%b MID=%b HIGH=%b | MOTOR=%b",
$time, low, mid, high, motor_on);
end
endmodule

water_level.vcd
$date
	Thu Nov 13 22:01:03 2025
$end
$version
	Icarus Verilog
$end
$timescale
	1s
$end
$scope module tb_water_level_controller $end
$var wire 1 ! motor_on $end
$var reg 1 " clk $end
$var reg 1 # high $end
$var reg 1 $ low $end
$var reg 1 % mid $end
$var reg 1 & reset $end
$scope module uut $end
$var wire 1 " clk $end
$var wire 1 # high $end
$var wire 1 $ low $end
$var wire 1 % mid $end
$var wire 1 & reset $end
$var parameter 2 ' EMPTY $end
$var parameter 2 ( FILLING $end
$var parameter 2 ) FULL $end
$var reg 2 * current_state [1:0] $end
$var reg 1 ! motor_on $end
$var reg 2 + next_state [1:0] $end
$upscope $end
$upscope $end
$enddefinitions $end
$comment Show the parameter values. $end
$dumpall
b10 )
b1 (
b0 '
$end
#0
$dumpvars
b1 +
b0 *
1&
0%
0$
0#
0"
1!
$end
#5
1"
#10
0"
0&
#15
b1 *
1"
#20
0"
#25
1"
#30
0"
1$
#35
1"
#40
0"
#45
1"
#50
0"
1%
#55
1"
#60
0"
#65
1"
#70
b10 +
0"
1#
#75
0!
b10 *
1"
#80
0"
#85
1"
#90
b1 +
0"
0#
0%
#95
1!
b1 *
1"
#100
0"
#105
1"
#110
0"
0$
